{
  "schema_version": 1,
  "source_sha": "68befdc84011c03a62872391b43ca2aba201de5d",
  "source_ref": "refs/heads/main",
  "workflow_run_id": "29922658374",
  "workflow_run_attempt": 1,
  "deployed_at": "2026-07-22T13:09:56.077Z",
  "deployment_url": "https://aiwebdesign-polar-index.caoheming139.workers.dev",
  "build": {
    "install": "npm install --no-audit --no-fund",
    "check": "npm run check",
    "command": "npm run build",
    "deploy": "cloudflare/wrangler-action@v3 command=deploy",
    "smoke_test": "passed"
  }
}
